timewinder/__init__.py
timewinder/__main__.py
timewinder/closure.py
timewinder/evaluation.py
timewinder/functions.py
timewinder/generators.py
timewinder/ltl.py
timewinder/object.py
timewinder/pause.py
timewinder/predicate.py
timewinder/process.py
timewinder/reinterp/__init__.py
timewinder/reinterp/interpreter.py
timewinder/reinterp/opcodes.py
timewinder/reinterp/predicate.py
timewinder/reinterp/process.py
timewinder/statetree/__init__.py
timewinder/statetree/cas.py
timewinder/statetree/controller.py
timewinder/statetree/tree.py
timewinder-0.1.dev1.dist-info/AUTHORS.md
timewinder-0.1.dev1.dist-info/LICENSE
timewinder-0.1.dev1.dist-info/METADATA
timewinder-0.1.dev1.dist-info/WHEEL
timewinder-0.1.dev1.dist-info/top_level.txt
timewinder-0.1.dev1.dist-info/RECORD
