Metadata-Version: 2.1
Name: timewinder
Version: 0.1.dev1
Summary: Temporal logic models for Python
Home-page: https://github.com/barakmich/timewinder
Author: Barak Michener
Author-email: me@barakmich.com
License: UNKNOWN
Platform: UNKNOWN
Classifier: License :: OSI Approved :: GNU General Public License v3 (GPLv3)
Classifier: Development Status :: 3 - Alpha
Classifier: Programming Language :: Python :: 3.8
Classifier: Programming Language :: Python :: 3.9
Requires-Python: >=3.8
Requires-Dist: dataclasses
Requires-Dist: msgpack
Requires-Dist: varname
